graphy2/Common.py
graphy2/Flow.py
graphy2/Seaborn.py
graphy2/StyleSheet.py
graphy2/__init__.py
graphy2/api.py
graphy2/core.py
graphy2/data.py
graphy2-0.4.2.dist-info/LICENSE
graphy2-0.4.2.dist-info/METADATA
graphy2-0.4.2.dist-info/WHEEL
graphy2-0.4.2.dist-info/top_level.txt
graphy2-0.4.2.dist-info/RECORD
