Metadata-Version: 2.1
Name: graphy2
Version: 0.4.2
Summary: graphy2: cross platform compatible Custom_Graphs and tables
Home-page: UNKNOWN
Author: Samuel Baker, Nina Di Cara, Oliwia Michalak
Author-email: samuelbaker.researcher@gmail.com
Maintainer: Samuel Baker, Nina Di Cara, Oliwia Michalak
Maintainer-email: samuelbaker.researcher@gmail.com
License: MIT
Download-URL: https://github.com/sbaker-dev/graphy2
Platform: UNKNOWN
Classifier: Intended Audience :: Science/Research
Classifier: Programming Language :: Python :: 3.7
Classifier: Programming Language :: Python :: 3.8
Classifier: License :: OSI Approved :: MIT License
Classifier: Topic :: Multimedia :: Graphics
Classifier: Operating System :: Microsoft :: Windows :: Windows 10
Requires-Python: >=3.6
Requires-Dist: seaborn (>=0.10.1)
Requires-Dist: pandas (>=1.0.3)
Requires-Dist: matplotlib (>=3.2.1)
Requires-Dist: cycler (>=0.10.0)
Requires-Dist: kiwisolver (>=1.2.0)
Requires-Dist: pyparsing (>=2.4.7)
Requires-Dist: python-dateutil (>=2.8.1)
Requires-Dist: pytz (>=2020.1)
Requires-Dist: numpy (>=1.18.4)
Requires-Dist: opencv-python (>=4.2.0.34)
Requires-Dist: csvObject (>=0.1)
